setup.py
dsnd_probability_das/Binomialdistribution.py
dsnd_probability_das/Gaussiandistribution.py
dsnd_probability_das/Generaldistribution.py
dsnd_probability_das/__init__.py
dsnd_probability_das.egg-info/PKG-INFO
dsnd_probability_das.egg-info/SOURCES.txt
dsnd_probability_das.egg-info/dependency_links.txt
dsnd_probability_das.egg-info/not-zip-safe
dsnd_probability_das.egg-info/top_level.txt