Metadata-Version: 1.0
Name: dsnd-probability-das
Version: 0.1
Summary: Gaussian distributions
Home-page: UNKNOWN
Author: Dipak Sutar
Author-email: sutardipak@nomail.com
License: UNKNOWN
Platform: UNKNOWN
